{"domain":{"alarm_control_panel":"Kontrol panel alarm","automation":"Otomasi","binary_sensor":"Sensor biner","calendar":"Kalender","camera":"Kamera","climate":"Cuaca","configurator":"Konfigurator","conversation":"Percakapan","cover":"Penutup","device_tracker":"Pelacak perangkat","fan":"Kipas angin","group":"Grup","hassio":"Hass.io","history_graph":"Riwayat Grafik","homeassistant":"Home Assistant","image_processing":"Pengolahan gambar","input_boolean":"Input boolean","input_datetime":"Input tanggal waktu","input_number":"Masukkan angka","input_select":"Input Pilihan","input_text":"Input teks","light":"Lampu","lock":"Kunci","lovelace":"Lovelace","mailbox":"Kotak pesan","media_player":"Pemutar media","notify":"Pemberitahuan","person":"Orang","plant":"Tanaman","proximity":"Kedekatan","remote":"Remot","scene":"Scene","script":"Skrip","sensor":"Sensor","sun":"Matahari","switch":"Sakelar","system_health":"System Health","updater":"Updater","vacuum":"Vakum","weblink":"Tautan web","zha":"ZHA","zwave":"Z-Wave"},"panel":{"calendar":"Kalender","config":"Konfigurasi","states":"Ikhtisar","map":"Peta","logbook":"Catatan Log","history":"Riwayat","mailbox":"Kotak pesan","shopping_list":"Daftar belanja","developer_tools":"Alat pengembang","profile":"Profile","dev-info":"Info"},"state":{"default":{"off":"Off","on":"On","unknown":"Tidak diketahui","unavailable":"Tidak tersedia"},"alarm_control_panel":{"armed":"Bersenjata","disarmed":"Dilucuti","armed_home":"Armed home","armed_away":"Armed away","armed_night":"Armed night","armed_custom_bypass":"Armed custom bypass","pending":"Tertunda","arming":"Mempersenjatai","disarming":"Melucuti","triggered":"Terpicu"},"automation":{"off":"Off","on":"On"},"binary_sensor":{"default":{"off":"Off","on":"On"},"battery":{"off":"Normal","on":"Rendah"},"cold":{"off":"Normal","on":"Dingin"},"connectivity":{"off":"Terputus","on":"Terhubung"},"door":{"off":"Tertutup","on":"Terbuka"},"garage_door":{"off":"Tertutup","on":"Terbuka"},"gas":{"off":"Kosong","on":"Terdeteksi"},"heat":{"off":"Normal","on":"Panas"},"lock":{"off":"Terkunci","on":"Terbuka"},"moisture":{"off":"Kering","on":"Basah"},"motion":{"off":"Tidak ada","on":"Terdeteksi"},"occupancy":{"off":"Tidak ada","on":"Terdeteksi"},"opening":{"off":"Tertutup","on":"Terbuka"},"presence":{"off":"Keluar","on":"Rumah"},"problem":{"off":"OK","on":"Masalah"},"safety":{"off":"Aman","on":"Tidak aman"},"smoke":{"off":"Tidak ada","on":"Terdeteksi"},"sound":{"off":"Tidak ada","on":"Terdeteksi"},"vibration":{"off":"Tidak ada","on":"Terdeteksi"},"window":{"off":"Tertutup","on":"Terbuka"}},"calendar":{"off":"Off","on":"On"},"camera":{"recording":"Merekam","streaming":"Streaming","idle":"Siaga"},"climate":{"off":"Off","heat":"Panas","cool":"Sejuk","heat_cool":"Heat/Cool","auto":"Auto","dry":"Kering","fan_only":"Hanya kipas","eco":"Eco","electric":"Petir","gas":"Gas","heat_pump":"Pompa pemanas","high_demand":"Permintaan yang tinggi","idle":"Siaga","manual":"Manual","on":"On","performance":"Kinerja"},"configurator":{"configure":"Konfigurasi","configured":"Terkonfigurasi"},"cover":{"open":"Buka","opening":"Membuka","closed":"Tertutup","closing":"Menutup","stopped":"Terhenti"},"device_tracker":{"home":"Rumah","not_home":"Keluar"},"fan":{"off":"Off","on":"On"},"group":{"off":"Off","on":"On","home":"Rumah","not_home":"Keluar","open":"Terbuka","opening":"Membuka","closed":"Tertutup","closing":"Menutup","stopped":"Tertutup","locked":"Terkunci","unlocked":"Terbuka","ok":"OK","problem":"Masalah"},"input_boolean":{"off":"Off","on":"On"},"light":{"off":"Off","on":"On"},"lock":{"locked":"Terkunci","unlocked":"Terbuka"},"media_player":{"off":"Off","on":"On","playing":"Memainkan","paused":"Jeda","idle":"Diam","standby":"Siaga"},"person":{"home":"Di rumah","not_home":"Mode jauh"},"plant":{"ok":"OK","problem":"Masalah"},"remote":{"off":"Off","on":"On"},"scene":{"scening":"Scening"},"script":{"off":"Off","on":"On"},"sensor":{"off":"Off","on":"On"},"sun":{"above_horizon":"Terbit","below_horizon":"Tenggelam"},"switch":{"off":"Off","on":"On"},"timer":{"active":"active","idle":"idle","paused":"paused"},"vacuum":{"cleaning":"Membersihkan","docked":"Berlabuh","error":"Kesalahan","idle":"Siaga","off":"Padam","on":"Menyala","paused":"Berhenti","returning":"Kembali ke dock"},"weather":{"clear-night":"Cerah, malam","cloudy":"Berawan","exceptional":"Exceptional","fog":"Kabut","hail":"Hujan es","lightning":"Petir","lightning-rainy":"Petir, hujan","partlycloudy":"Sebagian berawan","pouring":"Hujan lebat","rainy":"Hujan","snowy":"Bersalju","snowy-rainy":"Bersalju, hujan","sunny":"Cerah","windy":"Berangin","windy-variant":"Berangin"},"zwave":{"default":{"initializing":"Inisialisasi","dead":"Mati","sleeping":"Tidur","ready":"Siap"},"query_stage":{"initializing":"Inisialisasi ( {query_stage} )","dead":"Mati ({query_stage})"}}},"state_attributes":{"climate":{"fan_mode":{"off":"Off","on":"On","auto":"Auto"},"preset_mode":{"none":"None","eco":"Eco","away":"Away","boost":"Boost","comfort":"Comfort","home":"Home","sleep":"Sleep","activity":"Activity"},"hvac_action":{"off":"Off","heating":"Heating","cooling":"Cooling","drying":"Drying","idle":"Idle","fan":"Fan"}}},"state_badge":{"default":{"unknown":"Tak Tahu","unavailable":"Tak Ada","error":"Error","entity_not_found":"Entity Not Found"},"alarm_control_panel":{"armed":"Armed","disarmed":"Disarm","armed_home":"Armed","armed_away":"Armed","armed_night":"Armed","armed_custom_bypass":"Armed","pending":"Tunda","arming":"Arming","disarming":"Disarm","triggered":"Picu"},"device_tracker":{"home":"Rumah","not_home":"Keluar"},"person":{"home":"Rumah","not_home":"Keluar"}},"groups":{"system-admin":"Administrator","system-users":"Pengguna","system-read-only":"Read-Only Users"},"config_entry":{"disabled_by":{"user":"User","integration":"Integration","config_entry":"Config Entry"}},"ui":{"auth_store":{"ask":"Apakah Anda ingin menyimpan login ini?","decline":"Tidak, terima kasih","confirm":"Simpan login"},"card":{"alarm_control_panel":{"code":"Kode","clear_code":"Hapus","disarm":"Lucuti","arm_home":"Lengan rumah","arm_away":"Angkat tangan","arm_night":"Arm night","arm_custom_bypass":"Custom bypass"},"automation":{"last_triggered":"Terakhir terpicu","trigger":"Pemicu"},"camera":{"not_available":"Gambar tidak tersedia"},"climate":{"currently":"Saat ini","on_off":"Hidup / mati","target_temperature":"Target suhu","target_temperature_entity":"{name} target temperature","target_temperature_mode":"{name} target temperature {mode}","current_temperature":"{name} current temperature","heating":"{name} heating","cooling":"{name} cooling","high":"high","low":"low","target_humidity":"Target kelembaban","operation":"Operasi","fan_mode":"Mode kipas","swing_mode":"Mode ayunan","preset_mode":"Preset","away_mode":"Mode jauh","aux_heat":"Aux panas"},"counter":{"actions":{"increment":"increment","decrement":"decrement","reset":"reset"}},"cover":{"position":"Posisi","tilt_position":"Posisi kemiringan"},"fan":{"speed":"Kecepatan","oscillate":"Terombang-ambing","direction":"Arah","forward":"Forward","reverse":"Reverse"},"light":{"brightness":"Kecerahan","color_temperature":"Temperatur warna","white_value":"Nilai putih","effect":"Efek"},"lock":{"code":"Kode","lock":"Kunci","unlock":"Membuka"},"media_player":{"source":"Sumber","sound_mode":"Mode suara","text_to_speak":"Teks untuk berbicara"},"persistent_notification":{"dismiss":"Abaikan"},"scene":{"activate":"Aktifkan"},"script":{"execute":"Jalankan"},"timer":{"actions":{"start":"start","pause":"pause","cancel":"cancel","finish":"finish"}},"vacuum":{"actions":{"resume_cleaning":"Lanjutkan pembersihan","return_to_base":"Kembali ke dock","start_cleaning":"Mulai membersihkan","turn_on":"Nyalakan","turn_off":"Matikan"}},"water_heater":{"currently":"Saat ini","on_off":"On / off","target_temperature":"Target suhu","operation":"Operasi","away_mode":"Away mode"},"weather":{"attributes":{"air_pressure":"Tekanan udara","humidity":"Kelembaban","temperature":"Suhu","visibility":"Jarak pandang","wind_speed":"Kecepatan angin"},"cardinal_direction":{"e":"T","ene":"TTL","ese":"TMg","n":"U","ne":"TL","nne":"UTL","nw":"BL","nnw":"UBL","s":"S","se":"TG","sse":"SMg","ssw":"SBD","sw":"BD","w":"B","wnw":"BBL","wsw":"BBD"},"forecast":"Ramalan cuaca"}},"common":{"loading":"Memuat","cancel":"Batalkan","save":"Simpan","yes":"Yes","no":"No","successfully_saved":"Successfully saved"},"components":{"entity":{"entity-picker":{"entity":"Entiti","clear":"Clear","show_entities":"Show entities"}},"device-picker":{"clear":"Clear","show_devices":"Show devices","device":"Device"},"relative_time":{"past":"{time} lalu","future":"dalam {time}","never":"Tak pernah","duration":{"second":"{count} {count, plural,\n  one { detik }\n  other { detik }\n}","minute":"{count} {count, plural,\n  one { menit }\n  other { menit }\n}","hour":"{count} {count, plural,\n  one { jam }\n  other { jam }\n}","day":"{count} {count, plural,\n  one { hari }\n  other { hari }\n}","week":"{count} {count, plural,\n  one { minggu }\n  other { minggu }\n}"}},"history_charts":{"loading_history":"Memuat riwayat status ...","no_history_found":"Tidak ada riwayat status yang ditemukan."},"service-picker":{"service":"Layanan"}},"dialogs":{"voice_command":{"did_not_hear":"Home Assistant did not hear anything","found":"I found the following for you:","error":"Oops, an error has occurred","how_can_i_help":"How can I help?","label":"Type a question and press 'Enter'","label_voice":"Type and press 'Enter' or tap the microphone to speak"},"confirmation":{"cancel":"Cancel","ok":"OK","title":"Are you sure?"},"more_info_control":{"script":{"last_action":"Aksi Terakhir"},"sun":{"elevation":"Ketinggian","rising":"Terbit","setting":"Pengaturan"},"updater":{"title":"Petunjuk Pembaruan"}},"more_info_settings":{"save":"Simpan","name":"Nama","entity_id":"Entiti ID"},"options_flow":{"form":{"header":"Options"},"success":{"description":"Options successfully saved."}},"config_entry_system_options":{"title":"System Options for {integration}","enable_new_entities_label":"Enable newly added entities.","enable_new_entities_description":"If disabled, newly discovered entities for {integration} will not be automatically added to Home Assistant."},"zha_device_info":{"manuf":"by {manufacturer}","no_area":"No Area","buttons":{"add":"Add Devices","remove":"Remove Device","reconfigure":"Reconfigure Device"},"services":{"reconfigure":"Reconfigure ZHA device (heal device). Use this if you are having issues with the device. If the device in question is a battery powered device please ensure it is awake and accepting commands when you use this service.","updateDeviceName":"Set a custom name for this device in the device registry.","remove":"Remove a device from the Zigbee network."},"quirk":"Quirk","last_seen":"Last Seen","power_source":"Power Source","unknown":"Unknown","zha_device_card":{"device_name_placeholder":"User given name","area_picker_label":"Area","update_name_button":"Update Name"}},"domain_toggler":{"title":"Toggle Domains"}},"duration":{"second":"{count}{count, plural,\n  one { detik }\n  other { detik }\n}","minute":"{count} {count, plural,\n  one { menit }\n  other { menit }\n}","hour":"{count} {count, plural,\n  one { jam }\n  other { jam }\n}","day":"{count}{count, plural,\n  one { hari }\n  other { hari }\n}","week":"{count}{count, plural,\n  one { minggu }\n  other { minggu }\n}"},"login-form":{"password":"Kata sandi","remember":"Ingat","log_in":"Masuk"},"notification_drawer":{"click_to_configure":"Klik tombol untuk mengonfigurasi {entity}","empty":"Tidak ada pemberitahuan","title":"Pemberitahuan"},"notification_toast":{"service_call_failed":"Gagal memanggil layanan {service} .","connection_lost":"Koneksi terputus. Menghubungkan kembali ...","triggered":"Triggered {name}","entity_turned_off":"{entity} sudah dimatikan.","entity_turned_on":"{entity} sudah dinyalakan.","service_called":"Layanan {service} dipanggil."},"sidebar":{"external_app_configuration":"Konfigurasi Aplikasi","sidebar_toggle":"Sidebar Toggle","log_out":"Keluar"},"panel":{"lovelace":{"cards":{"confirm_delete":"Are you sure you want to delete this card?","empty_state":{"title":"Selamat datang di rumah","no_devices":"Halaman ini memungkinkan Anda untuk mengontrol perangkat Anda, namun sepertinya Anda belum mengatur perangkat. Buka halaman integrasi untuk memulai.","go_to_integrations_page":"Buka halaman integrasi."},"shopping-list":{"checked_items":"Checked items","clear_items":"Clear checked items","add_item":"Add item"},"picture-elements":{"hold":"Hold:","tap":"Tap:","navigate_to":"Navigate to {location}","url":"Open window to {url_path}","toggle":"Toggle {name}","call_service":"Call service {name}","more_info":"Tampilkan lebih banyak info: {name}"}},"unused_entities":{"title":"Unused entities","available_entities":"These are the entities that you have available, but are not in your Lovelace UI yet.","select_to_add":"Select the entities you want to add to a card and then click the add card button.","entity":"Entity","entity_id":"Entity ID","domain":"Domain","last_changed":"Last Changed"},"views":{"confirm_delete":"Are you sure you want to delete this view?","existing_cards":"You can't delete a view that has cards in it. Remove the cards first."},"menu":{"configure_ui":"Configure UI","help":"Help","refresh":"Refresh","close":"Close"},"editor":{"header":"Edit UI","menu":{"open":"Open Lovelace menu","raw_editor":"Raw config editor"},"raw_editor":{"header":"Edit Konfigurasi","save":"Simpan","unsaved_changes":"Perubahan yang belum disimpan","saved":"Disimpan","confirm_unsaved_changes":"You have unsaved changes, are you sure you want to exit?","confirm_unsaved_comments":"Your config contains comment(s), these will not be saved. Do you want to continue?","error_parse_yaml":"Unable to parse YAML: {error}","error_invalid_config":"Your config is not valid: {error}","error_save_yaml":"Unable to save YAML: {error}"},"edit_lovelace":{"header":"Title of your Lovelace UI","explanation":"This title is shown above all your views in Lovelace.","edit_title":"Edit title"},"edit_view":{"header":"View Configuration","header_name":"{name} View Configuration","add":"Add view","edit":"Edit view","delete":"Delete view","move_left":"Move view left","move_right":"Move view right"},"edit_card":{"header":"Card Configuration","pick_card":"Which card would you like to add?","pick_card_view_title":"Which card would you like to add to your {name} view?","toggle_editor":"Toggle Editor","show_visual_editor":"Show Visual Editor","show_code_editor":"Show Code Editor","add":"Add Card","edit":"Edit","delete":"Hapus","move":"Move to View","options":"More options"},"save_config":{"header":"Take control of your Lovelace UI","para":"By default Home Assistant will maintain your user interface, updating it when new entities or Lovelace components become available. If you take control we will no longer make changes automatically for you.","para_sure":"Apakah Anda yakin ingin mengendalikan antarmuka pengguna Anda?","cancel":"Never mind","save":"Take control"},"migrate":{"header":"Configuration Incompatible","para_no_id":"This element doesn't have an ID. Please add an ID to this element in 'ui-lovelace.yaml'.","para_migrate":"Home Assistant can add ID's to all your cards and views automatically for you by pressing the 'Migrate config' button.","migrate":"Migrate config"},"card":{"alarm-panel":{"name":"Alarm Panel","available_states":"Available States"},"conditional":{"name":"Conditional"},"config":{"required":"Required","optional":"Optional"},"entities":{"name":"Entities","show_header_toggle":"Show Header Toggle?","toggle":"Toggle entities."},"entity-button":{"name":"Entity Button"},"entity-filter":{"name":"Entity Filter"},"gauge":{"name":"Gauge","severity":{"define":"Define Severity?","green":"Green","red":"Red","yellow":"Yellow"}},"glance":{"name":"Glance","columns":"Columns"},"history-graph":{"name":"History Graph"},"horizontal-stack":{"name":"Horizontal Stack"},"iframe":{"name":"iFrame"},"light":{"name":"Light"},"generic":{"aspect_ratio":"Aspect Ratio","camera_image":"Camera Entity","camera_view":"Camera View","entities":"Entities","entity":"Entity","hold_action":"Hold Action","hours_to_show":"Hours to Show","icon":"Icon","icon_height":"Icon Height","image":"Image Path","maximum":"Maximum","minimum":"Minimum","name":"Name","refresh_interval":"Refresh Interval","show_icon":"Show Icon?","show_name":"Show Name?","show_state":"Show State?","tap_action":"Tap Action","title":"Title","theme":"Theme","unit":"Unit","url":"Url"},"map":{"name":"Map","geo_location_sources":"Geolocation Sources","dark_mode":"Dark Mode?","default_zoom":"Default Zoom","source":"Source"},"markdown":{"name":"Markdown","content":"Content"},"media-control":{"name":"Media Control"},"picture":{"name":"Picture"},"picture-elements":{"name":"Picture Elements"},"picture-entity":{"name":"Picture Entity"},"picture-glance":{"name":"Picture Glance"},"plant-status":{"name":"Plant Status"},"sensor":{"name":"Sensor","graph_detail":"Graph Detail","graph_type":"Graph Type"},"shopping-list":{"name":"Shopping List"},"thermostat":{"name":"Thermostat"},"vertical-stack":{"name":"Vertical Stack"},"weather-forecast":{"name":"Weather Forecast"}},"view":{"panel_mode":{"title":"Panel Mode?","description":"This renders the first card at full width; other cards in this view will not be rendered."}}},"warning":{"entity_not_found":"Entity not available: {entity}","entity_non_numeric":"Entity is non-numeric: {entity}"},"changed_toast":{"message":"The Lovelace config was updated, would you like to refresh?","refresh":"Refresh"},"reload_lovelace":"Reload Lovelace"},"custom":{"external_panel":{"question_trust":"Do you trust the external panel {name} at {link}?","complete_access":"It will have access to all data in Home Assistant.","hide_message":"Check docs for the panel_custom component to hide this message"}}}},"attribute":{"weather":{"humidity":"Kelembaban","visibility":"Jarak pandang","wind_speed":"Kecepatan angin"}}}