{"domain":{"alarm_control_panel":"Alarm control panel","automation":"Automation","binary_sensor":"Binary sensor","calendar":"Calendar","camera":"Camera","climate":"Climate","configurator":"Configurator","conversation":"Conversation","cover":"Cover","device_tracker":"Device tracker","fan":"Fan","group":"Group","hassio":"Hass.io","history_graph":"History graph","homeassistant":"Home Assistant","image_processing":"Image processing","input_boolean":"Input boolean","input_datetime":"Input datetime","input_number":"Input number","input_select":"Input select","input_text":"உரை உள்ளிடு","light":"மின் விளக்கு","lock":"பூட்டு","lovelace":"Lovelace","mailbox":"அஞ்சல் பெட்டி","media_player":"மீடியா பிளேயர்","notify":"தெரிவி","person":"Person","plant":"Plant","proximity":"Proximity","remote":"ரிமோட்","scene":"காட்சி","script":"ஸ்கிரிப்ட்","sensor":"சென்சார்","sun":"சூரியன்","switch":"ஸ்விட்ச்","system_health":"System Health","updater":"அப்டேட்டர்","vacuum":"Vacuum","weblink":"இணையதள இணைப்பு","zha":"ZHA","zwave":"Z-Wave"},"panel":{"calendar":"Calendar","config":"அமைப்புகள்","states":"கண்ணோட்டம்","map":"வரைபடம்","logbook":"பதிவேடுகள்","history":"வரலாறு","mailbox":"அஞ்சல் பெட்டி","shopping_list":"பொருட்கள் பட்டியல்","developer_tools":"Developer Tools","profile":"Profile"},"state":{"default":{"off":"ஆஃப்","on":"ஆன்","unknown":"தெரியவில்லை","unavailable":"கிடைக்கவில்லை"},"alarm_control_panel":{"armed":"எச்சரிக்கை ஒலி அமைக்கப்பட்டுள்ளது","disarmed":"எச்சரிக்கை ஒலி அமைக்கப்படவில்லை","armed_home":"எச்சரிக்கை ஒலி முகப்பு","armed_away":"எச்சரிக்கை ஒலி வெளியே","armed_night":"எச்சரிக்கை ஒலி இரவில்","armed_custom_bypass":"விருப்ப எச்சரிக்கை ஒலி","pending":"நிலுவையில்","arming":"எச்சரிக்கை ஒலி அமைக்கிறது","disarming":"எச்சரிக்கை ஒலி நீக்கம்","triggered":"தூண்டப்படுகிறது"},"automation":{"off":"ஆஃப்","on":"ஆன் "},"binary_sensor":{"default":{"off":"ஆஃப்","on":"ஆன் "},"battery":{"off":"Normal","on":"Low"},"cold":{"off":"Normal","on":"Cold"},"connectivity":{"off":"Disconnected","on":"Connected"},"door":{"off":"Closed","on":"Open"},"garage_door":{"off":"Closed","on":"Open"},"gas":{"off":"தெளிவு","on":"கண்டறியப்பட்டது"},"heat":{"off":"ஆஃப்","on":"சூடான"},"lock":{"off":"Locked","on":"Unlocked"},"moisture":{"off":"உலர்","on":"ஈரம்"},"motion":{"off":"தெளிவு ","on":"கண்டறியப்பட்டது"},"occupancy":{"off":"தெளிவு ","on":"கண்டறியப்பட்டது"},"opening":{"off":"மூடப்பட்டது","on":"திறக்கப்பட்டுள்ளது"},"presence":{"off":"தொலைவில்","on":"முகப்பு"},"problem":{"off":"சரி","on":"சிக்கல்"},"safety":{"off":"பாதுகாப்பான","on":"பாதுகாப்பற்ற"},"smoke":{"off":"தெளிவு ","on":"கண்டறியப்பட்டது"},"sound":{"off":"தெளிவு ","on":"கண்டறியப்பட்டது"},"vibration":{"off":"தெளிவு ","on":"கண்டறியப்பட்டது"},"window":{"off":"மூடப்பட்டுள்ளது","on":"திறக்கப்பட்டுள்ளது"}},"calendar":{"off":"ஆஃப்","on":"ஆன் "},"camera":{"recording":"பதிவு","streaming":"ஸ்ட்ரீமிங்","idle":"பணியின்றி"},"climate":{"off":"ஆஃப்","heat":"வெப்பம்","cool":"குளிர்","heat_cool":"Heat/Cool","auto":"தானாக இயங்குதல்","dry":"உலர்ந்த","fan_only":"விசிறி மட்டும்","eco":"சுற்றுச்சூழல்","electric":"மின்சார","gas":"வாயு","heat_pump":"வெப்ப பம்ப்","high_demand":"அதிக தேவை","idle":"பணியின்றி","manual":"கையேடு","on":"ஆன் ","performance":"செயல்திறன்"},"configurator":{"configure":"உள்ளமை","configured":"உள்ளமைக்கப்பட்டது"},"cover":{"open":"திறக்கப்பட்டுள்ளது","opening":"திறக்கிறது","closed":"மூடப்பட்டது","closing":"மூடுகிறது","stopped":"நிறுத்தப்பட்டது"},"device_tracker":{"home":"முகப்பு","not_home":"தொலைவில்"},"fan":{"off":"ஆஃப்","on":"விசிறி ஆன்"},"group":{"off":"ஆஃப்","on":"ஆன்","home":"வீட்டில்","not_home":"தொலைவில்","open":"திறக்கப்பட்டுள்ளது ","opening":"திறக்கிறது ","closed":"மூடப்பட்டுள்ளது ","closing":"மூடுகிறது ","stopped":"நிறுத்தப்பட்டுள்ளது ","locked":"பூட்டப்பட்டுள்ளது ","unlocked":"திறக்கப்பட்டுள்ளது ","ok":"சரி","problem":"சிக்கல்"},"input_boolean":{"off":"ஆஃப்","on":"ஆன்"},"light":{"off":"ஆஃப்","on":"ஆன்"},"lock":{"locked":"பூட்டப்பட்டது","unlocked":"திறக்கப்பட்டது"},"media_player":{"off":"ஆஃப்","on":"ஆன்","playing":"விளையாடுதல்","paused":"இடைநிறுத்தப்பட்டுள்ளது","idle":"பணியின்றி","standby":"காத்திரு"},"person":{"home":"Home","not_home":"Away"},"plant":{"ok":"சரி","problem":"சிக்கல்"},"remote":{"off":"ஆஃப்","on":"ஆன்"},"scene":{"scening":"காட்சி"},"script":{"off":"ஆஃப்","on":"ஆன்"},"sensor":{"off":"ஆஃப்","on":"ஆன்"},"sun":{"above_horizon":"தொடுவானத்திற்கு மேலே","below_horizon":"தொடுவானத்திற்குக் கீழே"},"switch":{"off":"ஆஃப்","on":"ஆன்"},"timer":{"active":"active","idle":"idle","paused":"paused"},"vacuum":{"cleaning":"Cleaning","docked":"Docked","error":"Error","idle":"Idle","off":"Off","on":"On","paused":"Paused","returning":"Returning to dock"},"weather":{"clear-night":"Clear, night","cloudy":"Cloudy","exceptional":"Exceptional","fog":"Fog","hail":"Hail","lightning":"Lightning","lightning-rainy":"Lightning, rainy","partlycloudy":"Partly cloudy","pouring":"Pouring","rainy":"Rainy","snowy":"Snowy","snowy-rainy":"Snowy, rainy","sunny":"Sunny","windy":"Windy","windy-variant":"Windy"},"zwave":{"default":{"initializing":"துவக்குகிறது","dead":"இறந்துவிட்டது","sleeping":"தூங்குகின்றது","ready":"தயார்"},"query_stage":{"initializing":"துவக்குகிறது ( {query_stage} )","dead":"இறந்துவிட்டது ({query_stage})"}}},"state_attributes":{"climate":{"fan_mode":{"off":"Off","on":"On","auto":"Auto"},"preset_mode":{"none":"None","eco":"Eco","away":"Away","boost":"Boost","comfort":"Comfort","home":"Home","sleep":"Sleep","activity":"Activity"},"hvac_action":{"off":"Off","heating":"Heating","cooling":"Cooling","drying":"Drying","idle":"Idle","fan":"Fan"}}},"state_badge":{"default":{"unknown":"தெரியாத","unavailable":"கிடைக்கவில்லை","error":"Error","entity_not_found":"Entity Not Found"},"alarm_control_panel":{"armed":"எச்சரிக்கை ஒலி அமைக்கப்பட்டுள்ளது","disarmed":"எச்சரிக்கை ஒலி அமைக்கப்படவில்லை","armed_home":"எச்சரிக்கை ஒலி அமைக்கப்பட்டுள்ளது ","armed_away":"எச்சரிக்கை ஒலி அமைக்கப்பட்டுள்ளது ","armed_night":"எச்சரிக்கை ஒலி அமைக்கப்பட்டுள்ளது","armed_custom_bypass":"எச்சரிக்கை ஒலி அமைக்கப்பட்டுள்ளது","pending":"கிடப்பில்","arming":"எச்சரிக்கை ஒலி அமைக்கிறது","disarming":"எச்சரிக்கை ஒலி அமைக்கப்படவில்லை","triggered":"தூண்ட"},"device_tracker":{"home":"வீட்டில்","not_home":"தொலைவில்"},"person":{"home":"Home","not_home":"Away"}},"groups":{"system-admin":"Administrators","system-users":"Users","system-read-only":"Read-Only Users"},"config_entry":{"disabled_by":{"user":"User","integration":"Integration","config_entry":"Config Entry"}},"ui":{"auth_store":{"ask":"Do you want to save this login?","decline":"No thanks","confirm":"Save login"},"card":{"alarm_control_panel":{"code":"Code","clear_code":"Clear","disarm":"Disarm","arm_home":"Arm home","arm_away":"Arm away","arm_night":"Arm night","arm_custom_bypass":"Custom bypass"},"automation":{"last_triggered":"Last triggered","trigger":"Trigger"},"camera":{"not_available":"Image not available"},"climate":{"currently":"Currently","on_off":"On / off","target_temperature":"Target temperature","target_temperature_entity":"{name} target temperature","target_temperature_mode":"{name} target temperature {mode}","current_temperature":"{name} current temperature","heating":"{name} heating","cooling":"{name} cooling","high":"high","low":"low","target_humidity":"Target humidity","operation":"Operation","fan_mode":"Fan mode","swing_mode":"Swing mode","preset_mode":"Preset","away_mode":"Away mode","aux_heat":"Aux heat"},"counter":{"actions":{"increment":"increment","decrement":"decrement","reset":"reset"}},"cover":{"position":"Position","tilt_position":"Tilt position"},"fan":{"speed":"Speed","oscillate":"Oscillate","direction":"Direction","forward":"Forward","reverse":"Reverse"},"light":{"brightness":"Brightness","color_temperature":"Color temperature","white_value":"White value","effect":"Effect"},"lock":{"code":"Code","lock":"Lock","unlock":"Unlock"},"media_player":{"source":"Source","sound_mode":"Sound mode","text_to_speak":"Text to speak"},"persistent_notification":{"dismiss":"Dismiss"},"scene":{"activate":"Activate"},"script":{"execute":"Execute"},"timer":{"actions":{"start":"start","pause":"pause","cancel":"cancel","finish":"finish"}},"vacuum":{"actions":{"resume_cleaning":"Resume cleaning","return_to_base":"Return to dock","start_cleaning":"Start cleaning","turn_on":"Turn on","turn_off":"Turn off"}},"water_heater":{"currently":"Currently","on_off":"On / off","target_temperature":"Target temperature","operation":"Operation","away_mode":"Away mode"},"weather":{"attributes":{"air_pressure":"Air pressure","humidity":"Humidity","temperature":"Temperature","visibility":"Visibility","wind_speed":"Wind speed"},"cardinal_direction":{"e":"E","ene":"ENE","ese":"ESE","n":"N","ne":"NE","nne":"NNE","nw":"NW","nnw":"NNW","s":"S","se":"SE","sse":"SSE","ssw":"SSW","sw":"SW","w":"W","wnw":"WNW","wsw":"WSW"},"forecast":"Forecast"}},"common":{"loading":"Loading","cancel":"Cancel","save":"Save","yes":"Yes","no":"No","successfully_saved":"Successfully saved"},"components":{"entity":{"entity-picker":{"entity":"Entity","clear":"Clear","show_entities":"Show entities"}},"device-picker":{"clear":"Clear","show_devices":"Show devices","device":"Device"},"relative_time":{"past":"{time} ago","future":"In {time}","never":"Never","duration":{"second":"{count} {count, plural,\n  one {second}\n  other {seconds}\n}","minute":"{count} {count, plural,\n  one {minute}\n  other {minutes}\n}","hour":"{count} {count, plural,\n  one {hour}\n  other {hours}\n}","day":"{count} {count, plural,\n  one {day}\n  other {days}\n}","week":"{count} {count, plural,\n  one {week}\n  other {weeks}\n}"}},"history_charts":{"loading_history":"Loading state history...","no_history_found":"No state history found."},"service-picker":{"service":"Service"}},"dialogs":{"voice_command":{"did_not_hear":"Home Assistant did not hear anything","found":"I found the following for you:","error":"Oops, an error has occurred","how_can_i_help":"How can I help?","label":"Type a question and press 'Enter'","label_voice":"Type and press 'Enter' or tap the microphone to speak"},"confirmation":{"cancel":"Cancel","ok":"OK","title":"Are you sure?"},"more_info_control":{"script":{"last_action":"Last Action"},"sun":{"elevation":"Elevation","rising":"Rising","setting":"Setting"},"updater":{"title":"Update Instructions"}},"more_info_settings":{"save":"Save","name":"Name Override","entity_id":"Entity ID"},"options_flow":{"form":{"header":"Options"},"success":{"description":"Options successfully saved."}},"config_entry_system_options":{"title":"System Options for {integration}","enable_new_entities_label":"Enable newly added entities.","enable_new_entities_description":"If disabled, newly discovered entities for {integration} will not be automatically added to Home Assistant."},"zha_device_info":{"manuf":"by {manufacturer}","no_area":"No Area","buttons":{"add":"Add Devices","remove":"Remove Device","reconfigure":"Reconfigure Device"},"services":{"reconfigure":"Reconfigure ZHA device (heal device). Use this if you are having issues with the device. If the device in question is a battery powered device please ensure it is awake and accepting commands when you use this service.","updateDeviceName":"Set a custom name for this device in the device registry.","remove":"Remove a device from the Zigbee network."},"quirk":"Quirk","last_seen":"Last Seen","power_source":"Power Source","unknown":"Unknown","zha_device_card":{"device_name_placeholder":"User given name","area_picker_label":"Area","update_name_button":"Update Name"}},"domain_toggler":{"title":"Toggle Domains"}},"duration":{"second":"{count} {count, plural,\n  one {second}\n  other {seconds}\n}","minute":"{count} {count, plural,\n  one {minute}\n  other {minutes}\n}","hour":"{count} {count, plural,\n  one {hour}\n  other {hours}\n}","day":"{count} {count, plural,\n  one {day}\n  other {days}\n}","week":"{count} {count, plural,\n  one {week}\n  other {weeks}\n}"},"login-form":{"password":"கடவுச்சொல்","remember":"நினைவில் கொள்","log_in":"உள் நுழை"},"notification_drawer":{"click_to_configure":"Click button to configure {entity}","empty":"No Notifications","title":"Notifications"},"notification_toast":{"service_call_failed":"Failed to call service {service}.","connection_lost":"Connection lost. Reconnecting…","triggered":"Triggered {name}"},"sidebar":{"external_app_configuration":"App Configuration","sidebar_toggle":"Sidebar Toggle","log_out":"வெளியேறு"},"panel":{"lovelace":{"cards":{"confirm_delete":"Are you sure you want to delete this card?","empty_state":{"title":"Welcome Home","no_devices":"This page allows you to control your devices, however it looks like you have no devices set up yet. Head to the integrations page to get started.","go_to_integrations_page":"Go to the integrations page."},"shopping-list":{"checked_items":"Checked items","clear_items":"Clear checked items","add_item":"Add item"},"picture-elements":{"hold":"Hold:","tap":"Tap:","navigate_to":"Navigate to {location}","url":"Open window to {url_path}","toggle":"Toggle {name}","call_service":"Call service {name}","more_info":"Show more-info: {name}"}},"unused_entities":{"title":"Unused entities","available_entities":"These are the entities that you have available, but are not in your Lovelace UI yet.","select_to_add":"Select the entities you want to add to a card and then click the add card button.","entity":"Entity","entity_id":"Entity ID","domain":"Domain","last_changed":"Last Changed"},"views":{"confirm_delete":"Are you sure you want to delete this view?","existing_cards":"You can't delete a view that has cards in it. Remove the cards first."},"menu":{"configure_ui":"Configure UI","help":"Help","refresh":"Refresh","close":"Close"},"editor":{"header":"Edit UI","menu":{"open":"Open Lovelace menu","raw_editor":"Raw config editor"},"raw_editor":{"header":"Edit Config","save":"Save","unsaved_changes":"Unsaved changes","saved":"Saved","confirm_unsaved_changes":"You have unsaved changes, are you sure you want to exit?","confirm_unsaved_comments":"Your config contains comment(s), these will not be saved. Do you want to continue?","error_parse_yaml":"Unable to parse YAML: {error}","error_invalid_config":"Your config is not valid: {error}","error_save_yaml":"Unable to save YAML: {error}"},"edit_lovelace":{"header":"Title of your Lovelace UI","explanation":"This title is shown above all your views in Lovelace.","edit_title":"Edit title"},"edit_view":{"header":"View Configuration","header_name":"{name} View Configuration","add":"Add view","edit":"Edit view","delete":"Delete view","move_left":"Move view left","move_right":"Move view right"},"edit_card":{"header":"Card Configuration","pick_card":"Which card would you like to add?","pick_card_view_title":"Which card would you like to add to your {name} view?","toggle_editor":"Toggle Editor","show_visual_editor":"Show Visual Editor","show_code_editor":"Show Code Editor","add":"Add Card","edit":"Edit","delete":"Delete Card","move":"Move to View","options":"More options"},"save_config":{"header":"Take control of your Lovelace UI","para":"By default Home Assistant will maintain your user interface, updating it when new entities or Lovelace components become available. If you take control we will no longer make changes automatically for you.","para_sure":"Are you sure you want to take control of your user interface?","cancel":"Never mind","save":"Take control"},"migrate":{"header":"Configuration Incompatible","para_no_id":"This element doesn't have an ID. Please add an ID to this element in 'ui-lovelace.yaml'.","para_migrate":"Home Assistant can add ID's to all your cards and views automatically for you by pressing the 'Migrate config' button.","migrate":"Migrate config"},"card":{"alarm-panel":{"name":"Alarm Panel","available_states":"Available States"},"conditional":{"name":"Conditional"},"config":{"required":"Required","optional":"Optional"},"entities":{"name":"Entities","show_header_toggle":"Show Header Toggle?","toggle":"Toggle entities."},"entity-button":{"name":"Entity Button"},"entity-filter":{"name":"Entity Filter"},"gauge":{"name":"Gauge","severity":{"define":"Define Severity?","green":"Green","red":"Red","yellow":"Yellow"}},"glance":{"name":"Glance","columns":"Columns"},"history-graph":{"name":"History Graph"},"horizontal-stack":{"name":"Horizontal Stack"},"iframe":{"name":"iFrame"},"light":{"name":"Light"},"generic":{"aspect_ratio":"Aspect Ratio","camera_image":"Camera Entity","camera_view":"Camera View","entities":"Entities","entity":"Entity","hold_action":"Hold Action","hours_to_show":"Hours to Show","icon":"Icon","icon_height":"Icon Height","image":"Image Path","maximum":"Maximum","minimum":"Minimum","name":"Name","refresh_interval":"Refresh Interval","show_icon":"Show Icon?","show_name":"Show Name?","show_state":"Show State?","tap_action":"Tap Action","title":"Title","theme":"Theme","unit":"Unit","url":"Url"},"map":{"name":"Map","geo_location_sources":"Geolocation Sources","dark_mode":"Dark Mode?","default_zoom":"Default Zoom","source":"Source"},"markdown":{"name":"Markdown","content":"Content"},"media-control":{"name":"Media Control"},"picture":{"name":"Picture"},"picture-elements":{"name":"Picture Elements"},"picture-entity":{"name":"Picture Entity"},"picture-glance":{"name":"Picture Glance"},"plant-status":{"name":"Plant Status"},"sensor":{"name":"Sensor","graph_detail":"Graph Detail","graph_type":"Graph Type"},"shopping-list":{"name":"Shopping List"},"thermostat":{"name":"Thermostat"},"vertical-stack":{"name":"Vertical Stack"},"weather-forecast":{"name":"Weather Forecast"}},"view":{"panel_mode":{"title":"Panel Mode?","description":"This renders the first card at full width; other cards in this view will not be rendered."}}},"warning":{"entity_not_found":"Entity not available: {entity}","entity_non_numeric":"Entity is non-numeric: {entity}"},"changed_toast":{"message":"The Lovelace config was updated, would you like to refresh?","refresh":"Refresh"},"reload_lovelace":"Reload Lovelace"},"custom":{"external_panel":{"question_trust":"Do you trust the external panel {name} at {link}?","complete_access":"It will have access to all data in Home Assistant.","hide_message":"Check docs for the panel_custom component to hide this message"}}}}}